odoo/addons/test_ssi_accounting_entry_mixin/README.rst
odoo/addons/test_ssi_accounting_entry_mixin/__init__.py
odoo/addons/test_ssi_accounting_entry_mixin/__manifest__.py
odoo/addons/test_ssi_accounting_entry_mixin/menu.xml
odoo/addons/test_ssi_accounting_entry_mixin/models/__init__.py
odoo/addons/test_ssi_accounting_entry_mixin/models/test_accounting_entry.py
odoo/addons/test_ssi_accounting_entry_mixin/security/ir.model.access.csv
odoo/addons/test_ssi_accounting_entry_mixin/static/description/icon.png
odoo/addons/test_ssi_accounting_entry_mixin/views/test_accounting_entry_views.xml
odoo14_addon_test_ssi_accounting_entry_mixin-14.0.2.1.0.dist-info/METADATA
odoo14_addon_test_ssi_accounting_entry_mixin-14.0.2.1.0.dist-info/WHEEL
odoo14_addon_test_ssi_accounting_entry_mixin-14.0.2.1.0.dist-info/top_level.txt
odoo14_addon_test_ssi_accounting_entry_mixin-14.0.2.1.0.dist-info/RECORD
